gitlog/__init__.py
gitlog/admin.py
gitlog/apps.py
gitlog/models.py
gitlog/tests.py
gitlog/urls.py
gitlog/utils.py
gitlog/views.py
gitlog/migrations/0001_initial.py
gitlog/migrations/0002_auto_20200204_1304.py
gitlog/migrations/0003_auto_20200206_1228.py
gitlog/migrations/__init__.py
gitlog/static/gitlog/daygram.css
gitlog/templates/gitlog/base.html
gitlog/templates/gitlog/index.html
gitlog/templates/gitlog/run.html
django_gitlog-0.2.dist-info/LICENSE
django_gitlog-0.2.dist-info/METADATA
django_gitlog-0.2.dist-info/WHEEL
django_gitlog-0.2.dist-info/top_level.txt
django_gitlog-0.2.dist-info/RECORD
